labpy/__init__.py
labpy/dsp.py
labpy/scpi_parser.py
labpy/series.py
labpy/server.py
labpy/types.py
labpy/utils.py
labpy/devices/__init__.py
labpy/devices/arduinopulsegen.py
labpy/devices/daqmx.py
labpy/devices/dmt_cs.py
labpy/devices/keithley_cs.py
labpy/devices/srs.py
labpy/devices/tb3000_aom_driver.py
labpy/devices/wavemeter.py
labpython-0.3.0.dist-info/METADATA
labpython-0.3.0.dist-info/WHEEL
labpython-0.3.0.dist-info/top_level.txt
labpython-0.3.0.dist-info/RECORD
