Metadata-Version: 2.1
Name: labpython
Version: 0.3.0
Summary: Collection of modules for controlling experimental setups.
Home-page: https://github.com/franciszekjuras/labpy
Author: Franciszek Juras
Author-email: franciszekjuras@gmail.com
License: MIT
Project-URL: Bug Tracker, https://github.com/franciszekjuras/labpy/issues
Project-URL: Documentation, https://franciszekjuras.github.io/labpy/labpy.html
Project-URL: Source Code, https://franciszekjuras.github.io/labpy/labpy.html
Keywords: experimental,physics,instrument,device,control,automation,data,acquisition
Platform: UNKNOWN
Requires-Python: >=3.8
Requires-Dist: numpy
Requires-Dist: scipy
Requires-Dist: jsbeautifier
Requires-Dist: pyvisa
Requires-Dist: pydaqmx (>=1.4.6)
Provides-Extra: full
Requires-Dist: statsmodels ; extra == 'full'
